<?xml version="1.0" encoding="UTF-8"?>
<resource xmlns:xsi="http://www.w3.org/2001/XMLSchema-instance" xsi:noNamespaceSchemaLocation="http://ofbiz.apache.org/dtds/ofbiz-properties.xsd">
    <property key="DemoApplication">
        <value xml:lang="en">Demo Application</value>
        <value xml:lang="zh">Demo应用程序</value>
        <value xml:lang="zh-TW">Demo應用程式</value>
    </property>
    <property key="DemoCompanyName">
        <value xml:lang="en">OFBiz: Demo</value>
        <value xml:lang="zh-TW">OFBiz: Demo</value>
    </property>
    <property key="DemoCompanySubtitle">
        <value xml:lang="en">Part of the Apache OFBiz Family of Open Source Software</value>
        <value xml:lang="it">Un modulo della famiglia di software open source Apache OFBiz</value>
        <value xml:lang="zh">开源软件OFBiz的组成部分</value>
        <value xml:lang="zh-TW">開源軟體OFBiz的組成部分</value>
    </property>
    <property key="DemoViewPermissionError">
        <value xml:lang="en">You are not allowed to view this page.</value>
        <value xml:lang="zh">不允许你浏览这个页面。</value>
        <value xml:lang="zh-TW">不允許您檢視這個頁面.</value>
    </property>

    <property key="DemoFind">
        <value xml:lang="en">Find</value>
        <value xml:lang="zh">查找</value>
    </property>
    <property key="DemoFirstName">
        <value xml:lang="en">First Name</value>
        <value xml:lang="zh">名</value>
    </property>
    <property key="DemoId">
        <value xml:lang="en">Demo Id</value>
        <value xml:lang="zh">Id</value>
    </property>
    <property key="DemoLastName">
        <value xml:lang="en">Last Name</value>
        <value xml:lang="zh">姓</value>
    </property>
    <property key="DemoType">
        <value xml:lang="en">Demo Type</value>
        <value xml:lang="zh">类型</value>
    </property>
    <property key="DemoComment">
        <value xml:lang="en">Demo Comment</value>
        <value xml:lang="zh">评论</value>
    </property>
    <property key="AddDemo">
        <value xml:lang="en">Add Demo</value>
        <value xml:lang="zh">新建</value>
    </property>
    <property key="ListDemo">
        <value xml:lang="en">List Demo</value>
        <value xml:lang="zh">列表</value>
    </property>
</resource>
